pytablereader/__init__.py
pytablereader/__version__.py
pytablereader/_acceptor.py
pytablereader/_common.py
pytablereader/_constant.py
pytablereader/_validator.py
pytablereader/error.py
pytablereader/formatter.py
pytablereader/interface.py
pytablereader/_logger/__init__.py
pytablereader/_logger/_logger.py
pytablereader/_logger/_null_logger.py
pytablereader/csv/__init__.py
pytablereader/csv/core.py
pytablereader/csv/formatter.py
pytablereader/factory/__init__.py
pytablereader/factory/_base.py
pytablereader/factory/_file.py
pytablereader/factory/_text.py
pytablereader/factory/_url.py
pytablereader/html/__init__.py
pytablereader/html/core.py
pytablereader/html/formatter.py
pytablereader/json/__init__.py
pytablereader/json/core.py
pytablereader/json/formatter.py
pytablereader/jsonlines/__init__.py
pytablereader/jsonlines/core.py
pytablereader/jsonlines/formatter.py
pytablereader/loadermanager/__init__.py
pytablereader/loadermanager/_base.py
pytablereader/loadermanager/_file.py
pytablereader/loadermanager/_text.py
pytablereader/loadermanager/_url.py
pytablereader/ltsv/__init__.py
pytablereader/ltsv/core.py
pytablereader/markdown/__init__.py
pytablereader/markdown/core.py
pytablereader/markdown/formatter.py
pytablereader/mediawiki/__init__.py
pytablereader/mediawiki/core.py
pytablereader/mediawiki/formatter.py
pytablereader/spreadsheet/__init__.py
pytablereader/spreadsheet/core.py
pytablereader/spreadsheet/excelloader.py
pytablereader/spreadsheet/gsloader.py
pytablereader/sqlite/__init__.py
pytablereader/sqlite/core.py
pytablereader/sqlite/formatter.py
pytablereader/tsv/__init__.py
pytablereader/tsv/core.py
pytablereader-0.31.4.dist-info/LICENSE
pytablereader-0.31.4.dist-info/METADATA
pytablereader-0.31.4.dist-info/WHEEL
pytablereader-0.31.4.dist-info/top_level.txt
pytablereader-0.31.4.dist-info/RECORD
