Metadata-Version: 2.1
Name: pytablereader
Version: 0.31.4
Summary: pytablereader is a Python library to load structured table data from files/strings/URL with various data format: CSV / Excel / Google-Sheets / HTML / JSON / LDJSON / LTSV / Markdown / SQLite / TSV.
Home-page: https://github.com/thombashi/pytablereader
Author: Tsuyoshi Hombashi
Author-email: tsuyoshi.hombashi@gmail.com
License: MIT License
Project-URL: Documentation, https://pytablereader.rtfd.io/
Project-URL: Source, https://github.com/thombashi/pytablereader
Project-URL: Tracker, https://github.com/thombashi/pytablereader/issues
Project-URL: Changlog, https://github.com/thombashi/pytablereader/releases
Keywords: table,reader,pandas,CSV,Excel,HTML,JSON,LTSV,Markdown,MediaWiki,TSV,SQLite
Classifier: Development Status :: 4 - Beta
Classifier: Intended Audience :: Developers
Classifier: Intended Audience :: Information Technology
Classifier: License :: OSI Approved :: MIT License
Classifier: Operating System :: OS Independent
Classifier: Programming Language :: Python :: 3
Classifier: Programming Language :: Python :: 3.7
Classifier: Programming Language :: Python :: 3.8
Classifier: Programming Language :: Python :: 3.9
Classifier: Programming Language :: Python :: 3.10
Classifier: Programming Language :: Python :: 3.11
Classifier: Programming Language :: Python :: 3 :: Only
Classifier: Programming Language :: Python :: Implementation :: CPython
Classifier: Programming Language :: Python :: Implementation :: PyPy
Classifier: Topic :: Database
Classifier: Topic :: Software Development :: Libraries
Classifier: Topic :: Software Development :: Libraries :: Python Modules
Classifier: Topic :: Text Processing
Requires-Python: >=3.7
Provides-Extra: all
Provides-Extra: excel
Provides-Extra: gs
Provides-Extra: logging
Provides-Extra: md
Provides-Extra: mediawiki
Provides-Extra: url
Provides-Extra: sqlite
Provides-Extra: test
License-File: LICENSE
